{"_type":"export","__export_format":4,"__export_date":"2019-08-01T20:53:10.584Z","__export_source":"insomnia.desktop.app:v6.5.4","resources":[{"_id":"req_abdc271498c8468db361a2d5de1d6334","authentication":{"token":"{{ token  }}","type":"bearer"},"body":{"mimeType":"multipart/form-data","params":[{"fileName":"/home/arli.machado/usuarios_lasa.xls","id":"pair_c88c6c5d1fd54873977cc15abe15b74d","name":"file","type":"file","value":""}]},"created":1564689891604,"description":"","headers":[{"id":"pair_c08deefc2885442facc780da8245c75c","name":"Content-Type","value":"multipart/form-data"}],"isPrivate":false,"metaSortKey":-1564689891604,"method":"POST","modified":1564691343194,"name":"Upload","parameters":[],"parentId":"fld_11161b66cf5e4fa786049b0facf8f09d","settingDisableRenderRequestBody":false,"settingEncodeUrl":true,"settingRebuildPath":true,"settingSendCookies":true,"settingStoreCookies":true,"url":"{{ base_url  }}/files","_type":"request"},{"_id":"fld_11161b66cf5e4fa786049b0facf8f09d","created":1564689871577,"description":"","environment":{},"environmentPropertyOrder":null,"metaSortKey":-1564689871577,"modified":1564689871577,"name":"Files","parentId":"wrk_1c8ea1c61894472b90394edaab633250","_type":"request_group"},{"_id":"wrk_1c8ea1c61894472b90394edaab633250","created":1564415766780,"description":"","modified":1564415766780,"name":"GoBarber","parentId":null,"_type":"workspace"},{"_id":"req_7f6056bb111c44afbee56f7e96b9a175","authentication":{},"body":{"mimeType":"application/json","text":"{\n\t\"email\": \"usuario@mail.com\",\n\t\"password\": \"123456\"\n}"},"created":1564418620046,"description":"","headers":[{"id":"pair_35b0294579cf44708538c5b36a93e456","name":"Content-Type","value":"application/json"}],"isPrivate":false,"metaSortKey":-1564208516472,"method":"POST","modified":1564691937492,"name":"Create (Copy)","parameters":[],"parentId":"fld_e3219a2cd87e4f25b482491a95c58dae","settingDisableRenderRequestBody":false,"settingEncodeUrl":true,"settingRebuildPath":true,"settingSendCookies":true,"settingStoreCookies":true,"url":"{{ base_url  }}/sessions","_type":"request"},{"_id":"fld_e3219a2cd87e4f25b482491a95c58dae","created":1564418616183,"description":"","environment":{},"environmentPropertyOrder":null,"metaSortKey":-1564418616183,"modified":1564418616183,"name":"Sessions","parentId":"wrk_1c8ea1c61894472b90394edaab633250","_type":"request_group"},{"_id":"req_8d0bd43fc82a4309a6dbf4eeafc34a76","authentication":{},"body":{"mimeType":"application/json","text":"{\n\t\"name\": \"usuario\",\n\t\"email\": \"usuario@mail.com\",\n\t\"password\": \"123456\"\n}"},"created":1564415815249,"description":"","headers":[{"id":"pair_35b0294579cf44708538c5b36a93e456","name":"Content-Type","value":"application/json"}],"isPrivate":false,"metaSortKey":-1564415815249,"method":"POST","modified":1564691924413,"name":"Create","parameters":[],"parentId":"fld_550fcf6bec35451782cc316a15f8f0a4","settingDisableRenderRequestBody":false,"settingEncodeUrl":true,"settingRebuildPath":true,"settingSendCookies":true,"settingStoreCookies":true,"url":"{{ base_url  }}/users","_type":"request"},{"_id":"fld_550fcf6bec35451782cc316a15f8f0a4","created":1564415775128,"description":"","environment":{},"environmentPropertyOrder":null,"metaSortKey":-1564415775129,"modified":1564415775128,"name":"Users","parentId":"wrk_1c8ea1c61894472b90394edaab633250","_type":"request_group"},{"_id":"req_d4c4a57e22804327965432c071919838","authentication":{"token":"{{ token  }}","type":"bearer"},"body":{"mimeType":"application/json","text":"{\n\t\"email\": \"teste@mail.com\",\n\t\"oldPassword\": \"12312312\",\n\t\"password\": \"123456\",\n\t\"confirmPassword\": \"123456\"\n}"},"created":1564420715789,"description":"","headers":[{"id":"pair_35b0294579cf44708538c5b36a93e456","name":"Content-Type","value":"application/json"}],"isPrivate":false,"metaSortKey":-1564312165860.5,"method":"PUT","modified":1564685257178,"name":"Update","parameters":[],"parentId":"fld_550fcf6bec35451782cc316a15f8f0a4","settingDisableRenderRequestBody":false,"settingEncodeUrl":true,"settingRebuildPath":true,"settingSendCookies":true,"settingStoreCookies":true,"url":"{{ base_url  }}/users","_type":"request"},{"_id":"env_092d72c9ce7d90ee2d4e5057c44cb75de96dc8dd","color":null,"created":1564415766971,"data":{"base_url":"http://localhost:3333","token":"eyJhbGciOiJIUzI1NiIsInR5cCI6IkpXVCJ9.eyJpZCI6NiwiaWF0IjoxNTY0NjkxOTM5LCJleHAiOjE1NjUyOTY3Mzl9.rkNY3fX13uNv1Pv6x-iKH2siNT-f7j5v6OiZvRAjZKA"},"dataPropertyOrder":{"&":["base_url","token"]},"isPrivate":false,"metaSortKey":1564415766971,"modified":1564691956866,"name":"Base Environment","parentId":"wrk_1c8ea1c61894472b90394edaab633250","_type":"environment"},{"_id":"jar_092d72c9ce7d90ee2d4e5057c44cb75de96dc8dd","cookies":[],"created":1564415766980,"modified":1564415766980,"name":"Default Jar","parentId":"wrk_1c8ea1c61894472b90394edaab633250","_type":"cookie_jar"}]}